[
    {
        "title": "80s",
        "collection": "dourfits",
        "trait": "Backgrounds",
        "layer": "background"
    },
    {
        "title": "Apricot",
        "xp": 0,
        "layer": "background",
        "hex": "#FFA466"
    },
    {
        "title": "Auburn",
        "xp": 0,
        "layer": "background",
        "hex": "#E16666"
    },
    {
        "title": "Baby Blue",
        "xp": 0,
        "layer": "background",
        "hex": "#A4C3E1"
    },
    {
        "title": "Black",
        "collection": "dourfits",
        "trait": "Backgrounds",
        "layer": "background"
    },
    {
        "title": "Blue Dots",
        "collection": "dourfits",
        "trait": "Backgrounds",
        "layer": "background"
    },
    {
        "title": "Blue Rays",
        "collection": "dourfits",
        "trait": "Backgrounds",
        "layer": "background"
    },
    {
        "title": "Brown",
        "collection": "dourdarcels",
        "trait": "Background",
        "layer": "background",
        "hex": "#4B2700"
    },
    {
        "title": "Cameras",
        "collection": "dourfits",
        "trait": "Backgrounds",
        "layer": "background"
    },
    {
        "title": "Camo",
        "collection": "dourfits",
        "trait": "Backgrounds",
        "layer": "background"
    },
    {
        "title": "Charcoal",
        "collection": "dourdarcels",
        "trait": "Background",
        "layer": "background",
        "hex": "#323232"
    },
    {
        "title": "Checkerboard",
        "collection": "dourfits",
        "trait": "Backgrounds",
        "layer": "background"
    },
    {
        "title": "City",
        "collection": "dourdarcels",
        "trait": "Background",
        "layer": "background",
        "hex": "#4B4B4B"
    },
    {
        "title": "Clouds",
        "collection": "dourdarcels",
        "trait": "Background",
        "layer": "background"
    },
    {
        "title": "Coffee",
        "collection": "dourdarcels",
        "trait": "Background",
        "layer": "background",
        "hex": "#7F5223"
    },
    {
        "title": "Concentric Circles",
        "collection": "dourfits",
        "trait": "Backgrounds",
        "layer": "background"
    },
    {
        "title": "Day Garden",
        "collection": "dourfits",
        "trait": "Backgrounds",
        "layer": "background"
    },
    {
        "title": "Diagonal Stripes",
        "collection": "dourfits",
        "trait": "Backgrounds",
        "layer": "background"
    },
    {
        "title": "Flames",
        "collection": "dourfits",
        "trait": "Backgrounds",
        "layer": "background"
    },
    {
        "title": "Forest",
        "collection": "dourdarcels",
        "trait": "Background",
        "layer": "background",
        "hex": "#004D00"
    },
    {
        "title": "Grass Green",
        "xp": 0,
        "layer": "background",
        "hex": "#66A466"
    },
    {
        "title": "Grid",
        "collection": "dourfits",
        "trait": "Backgrounds",
        "layer": "background"
    },
    {
        "title": "Leopard",
        "collection": "dourfits",
        "trait": "Backgrounds",
        "layer": "background"
    },
    {
        "title": "Lilac",
        "collection": "dourdarcels",
        "trait": "Background",
        "layer": "background",
        "hex": "#B182B5"
    },
    {
        "title": "Mauve",
        "collection": "dourdarcels",
        "trait": "Background",
        "layer": "background",
        "hex": "#7E5284"
    },
    {
        "title": "Mid Blue",
        "collection": "dourdarcels",
        "trait": "Background",
        "layer": "background",
        "hex": "#055083"
    },
    {
        "title": "Moss",
        "collection": "dourdarcels",
        "trait": "Background",
        "layer": "background",
        "hex": "#4B7F1C"
    },
    {
        "title": "Moss Rays",
        "collection": "dourfits",
        "trait": "Backgrounds",
        "layer": "background"
    },
    {
        "title": "Navy",
        "collection": "dourdarcels",
        "trait": "Background",
        "layer": "background",
        "hex": "#002456"
    },
    {
        "title": "New York Apartment",
        "collection": "dourfits",
        "trait": "Backgrounds",
        "layer": "background"
    },
    {
        "title": "New York Street",
        "collection": "dourfits",
        "trait": "Backgrounds",
        "layer": "background"
    },
    {
        "title": "Night Garden",
        "collection": "dourfits",
        "trait": "Backgrounds",
        "layer": "background"
    },
    {
        "title": "Orange",
        "collection": "dourdarcels",
        "trait": "Background",
        "layer": "background",
        "hex": "#E25201"
    },
    {
        "title": "Peach",
        "collection": "dourdarcels",
        "trait": "Background",
        "layer": "background",
        "hex": "#D98184"
    },
    {
        "title": "Peach Stripes",
        "collection": "dourfits",
        "trait": "Backgrounds",
        "layer": "background"
    },
    {
        "title": "Pink",
        "collection": "dourdarcels",
        "trait": "Background",
        "layer": "background",
        "hex": "#A03A8A"
    },
    {
        "title": "Pink Stripes",
        "collection": "dourfits",
        "trait": "Backgrounds",
        "layer": "background"
    },
    {
        "title": "Purple",
        "collection": "dourdarcels",
        "trait": "Background",
        "layer": "background",
        "hex": "#4F2154"
    },
    {
        "title": "Red",
        "collection": "dourdarcels",
        "trait": "Background",
        "layer": "background",
        "hex": "#A60707"
    },
    {
        "title": "Red Carpet",
        "collection": "dourfits",
        "trait": "Backgrounds",
        "layer": "background"
    },
    {
        "title": "Sky",
        "collection": "dourdarcels",
        "trait": "Background",
        "layer": "background",
        "hex": "#4680B2"
    },
    {
        "title": "Slate",
        "collection": "dourdarcels",
        "trait": "Background",
        "layer": "background",
        "hex": "#66686A"
    },
    {
        "title": "Smoke",
        "collection": "dourdarcels",
        "trait": "Background",
        "layer": "background",
        "hex": "#CBCFD0"
    },
    {
        "title": "Soft Yellow",
        "xp": 0,
        "layer": "background",
        "hex": "#FFE165"
    },
    {
        "title": "Space",
        "collection": "dourfits",
        "trait": "Backgrounds",
        "layer": "background"
    },
    {
        "title": "Special Black",
        "collection": "dourdarcels",
        "trait": "Background",
        "layer": "background",
        "hex": "#000000"
    },
    {
        "title": "Special Charcoal",
        "collection": "dourdarcels",
        "trait": "Background",
        "layer": "background",
        "hex": "#333333"
    },
    {
        "title": "Special Yellow",
        "collection": "dourdarcels",
        "trait": "Background",
        "layer": "background",
        "hex": "#FFCC33"
    },
    {
        "title": "Subway",
        "collection": "dourfits",
        "trait": "Backgrounds",
        "layer": "background"
    },
    {
        "title": "Tan",
        "collection": "dourdarcels",
        "trait": "Background",
        "layer": "background",
        "hex": "#AE804E"
    },
    {
        "title": "Taxi",
        "collection": "dourfits",
        "trait": "Backgrounds",
        "layer": "background"
    },
    {
        "title": "Versailles",
        "collection": "dourfits",
        "trait": "Backgrounds",
        "layer": "background"
    },
    {
        "title": "Wardrobe",
        "xp": 100,
        "layer": "background",
        "format": ".svg.png"
    },
    {
        "title": "White Dots",
        "collection": "dourfits",
        "trait": "Backgrounds",
        "layer": "background"
    },
    {
        "title": "Woodgrain",
        "collection": "dourfits",
        "trait": "Backgrounds",
        "layer": "background"
    },
    {
        "title": "Yellow",
        "collection": "dourdarcels",
        "trait": "Background",
        "layer": "background",
        "hex": "#FBBB02"
    }
]