[
	{
		"title": "Bandage Heels",
		"shortTitle": "Bandage",
		"trait": "Shoes & Legs",
		"layer": "shoes"
	},
	{
		"title": "Black Boots",
		"trait": "Shoes & Legs",
		"layer": "shoes"
	},
	{
		"title": "Black Heels",
		"trait": "Shoes & Legs",
		"layer": "shoes"
	},
	{
		"title": "Black Hi Tops",
		"trait": "Shoes & Legs",
		"layer": "shoes"
	},
	{
		"title": "Black High Top Sneakers",
		"trait": "Shoes & Legs",
		"layer": "shoes"
	},
	{
		"title": "Black Lace Up Boots",
		"trait": "Shoes & Legs",
		"layer": "shoes"
	},
	{
		"title": "Black Slides",
		"trait": "Shoes & Legs",
		"layer": "shoes"
	},
	{
		"title": "Black Sneakers",
		"trait": "Shoes & Legs",
		"layer": "shoes"
	},
	{
		"title": "Boat Shoes",
		"trait": "Shoes & Legs",
		"layer": "shoes"
	},
	{
		"title": "Brown Lace Up Boots",
		"trait": "Shoes & Legs",
		"layer": "shoes"
	}
]